README.md
setup.py
coinmarketcap/__init__.py
coinmarketcap/core.py
coinmarketcap.egg-info/PKG-INFO
coinmarketcap.egg-info/SOURCES.txt
coinmarketcap.egg-info/dependency_links.txt
coinmarketcap.egg-info/requires.txt
coinmarketcap.egg-info/top_level.txt