Metadata-Version: 1.1
Name: coinmarketcap
Version: 5.0.1
Summary: Python wrapper around the coinmarketcap.com API.
Home-page: https://github.com/barnumbirr/coinmarketcap
Author: Martin Simon
Author-email: me@martinsimon.me
License: Apache v2.0 License
Keywords: cryptocurrency,API,coinmarketcap,BTC,Bitcoin,LTC,Litecoin,XRP,Ripple,ETH,Ethereum 
Platform: UNKNOWN
Classifier: License :: OSI Approved :: Apache Software License
Classifier: Development Status :: 5 - Production/Stable
Classifier: Intended Audience :: Developers
Classifier: Programming Language :: Python
Classifier: Programming Language :: Python :: 2.7
Classifier: Programming Language :: Python :: 3.6
Classifier: Topic :: Software Development :: Libraries :: Python Modules
